clients_reporter/__init__.py
clients_reporter/__main__.py
clients_reporter/utils.py
clients_reporter_scochilloff-0.1.1.dist-info/METADATA
clients_reporter_scochilloff-0.1.1.dist-info/WHEEL
clients_reporter_scochilloff-0.1.1.dist-info/top_level.txt
clients_reporter_scochilloff-0.1.1.dist-info/RECORD
