Metadata-Version: 2.1
Name: clients_reporter_scochilloff
Version: 0.1.1
Summary: Пакет, создающий отчет по клиентам
Author-email: ScoChillOFF <cheatkiller12@gmail.com>
License: MIT
Requires-Python: >=3.12
Requires-Dist: pandas==2.2.3
